setup.cfg
setup.py
folslib/__init__.py
folslib/utils.py
folslib.egg-info/PKG-INFO
folslib.egg-info/SOURCES.txt
folslib.egg-info/dependency_links.txt
folslib.egg-info/top_level.txt