Metadata-Version: 1.1
Name: folslib
Version: 0.0.2
Summary: Folger's Python Lib
Home-page: https://github.com/folger/folslib
Author: Folger Lun
Author-email: lunbest@hotmail.com
License: UNKNOWN
Download-URL: https://github.com/folger/folslib/archive/0.0.2.tar.gz
Keywords: hello,world
Platform: UNKNOWN
